{"nodes": [{"id": "users_jinangokotano_documents_agentic_builder_projects_central_intelligence_backend_app_schemas_leads_py", "label": "leads.py", "file_type": "code", "source_file": "backend/app/schemas/leads.py", "source_location": "L1"}, {"id": "schemas_leads_leadrecord", "label": "LeadRecord", "file_type": "code", "source_file": "backend/app/schemas/leads.py", "source_location": "L25"}, {"id": "basemodel", "label": "BaseModel", "file_type": "code", "source_file": "", "source_location": ""}, {"id": "schemas_leads_leadlistresponse", "label": "LeadListResponse", "file_type": "code", "source_file": "backend/app/schemas/leads.py", "source_location": "L39"}, {"id": "schemas_leads_leadskpiresponse", "label": "LeadsKpiResponse", "file_type": "code", "source_file": "backend/app/schemas/leads.py", "source_location": "L53"}, {"id": "schemas_leads_leadvolumepoint", "label": "LeadVolumePoint", "file_type": "code", "source_file": "backend/app/schemas/leads.py", "source_location": "L67"}, {"id": "schemas_leads_sourcebreakdownitem", "label": "SourceBreakdownItem", "file_type": "code", "source_file": "backend/app/schemas/leads.py", "source_location": "L79"}, {"id": "schemas_leads_funnelstage", "label": "FunnelStage", "file_type": "code", "source_file": "backend/app/schemas/leads.py", "source_location": "L92"}, {"id": "schemas_leads_leadsstatsresponse", "label": "LeadsStatsResponse", "file_type": "code", "source_file": "backend/app/schemas/leads.py", "source_location": "L105"}, {"id": "schemas_leads_leadcallsummary", "label": "LeadCallSummary", "file_type": "code", "source_file": "backend/app/schemas/leads.py", "source_location": "L119"}, {"id": "schemas_leads_leadgoalsummary", "label": "LeadGoalSummary", "file_type": "code", "source_file": "backend/app/schemas/leads.py", "source_location": "L134"}, {"id": "schemas_leads_leadpainpointsummary", "label": "LeadPainPointSummary", "file_type": "code", "source_file": "backend/app/schemas/leads.py", "source_location": "L141"}, {"id": "schemas_leads_leadobjectionsummary", "label": "LeadObjectionSummary", "file_type": "code", "source_file": "backend/app/schemas/leads.py", "source_location": "L147"}, {"id": "schemas_leads_noterow", "label": "NoteRow", "file_type": "code", "source_file": "backend/app/schemas/leads.py", "source_location": "L153"}, {"id": "schemas_leads_leaddetailresponse", "label": "LeadDetailResponse", "file_type": "code", "source_file": "backend/app/schemas/leads.py", "source_location": "L163"}, {"id": "schemas_leads_updateleadrequest", "label": "UpdateLeadRequest", "file_type": "code", "source_file": "backend/app/schemas/leads.py", "source_location": "L188"}, {"id": "schemas_leads_createnoterequest", "label": "CreateNoteRequest", "file_type": "code", "source_file": "backend/app/schemas/leads.py", "source_location": "L201"}, {"id": "schemas_leads_leadhistoryevent", "label": "LeadHistoryEvent", "file_type": "code", "source_file": "backend/app/schemas/leads.py", "source_location": "L212"}, {"id": "schemas_leads_leadhistoryresponse", "label": "LeadHistoryResponse", "file_type": "code", "source_file": "backend/app/schemas/leads.py", "source_location": "L232"}, {"id": "schemas_leads_emailattachmentmeta", "label": "EmailAttachmentMeta", "file_type": "code", "source_file": "backend/app/schemas/leads.py", "source_location": "L248"}, {"id": "schemas_leads_emailmessagerow", "label": "EmailMessageRow", "file_type": "code", "source_file": "backend/app/schemas/leads.py", "source_location": "L256"}, {"id": "schemas_leads_emailthreadrow", "label": "EmailThreadRow", "file_type": "code", "source_file": "backend/app/schemas/leads.py", "source_location": "L270"}, {"id": "schemas_leads_emailthreadsresponse", "label": "EmailThreadsResponse", "file_type": "code", "source_file": "backend/app/schemas/leads.py", "source_location": "L280"}, {"id": "schemas_leads_documentrow", "label": "DocumentRow", "file_type": "code", "source_file": "backend/app/schemas/leads.py", "source_location": "L290"}, {"id": "schemas_leads_documentsresponse", "label": "DocumentsResponse", "file_type": "code", "source_file": "backend/app/schemas/leads.py", "source_location": "L303"}, {"id": "schemas_leads_rationale_1", "label": "Pydantic schemas for the leads API contract.  These models define the public res", "file_type": "rationale", "source_file": "backend/app/schemas/leads.py", "source_location": "L1"}, {"id": "schemas_leads_rationale_26", "label": "A single lead row returned in the paginated list.", "file_type": "rationale", "source_file": "backend/app/schemas/leads.py", "source_location": "L26"}, {"id": "schemas_leads_rationale_40", "label": "Paginated list of leads.", "file_type": "rationale", "source_file": "backend/app/schemas/leads.py", "source_location": "L40"}, {"id": "schemas_leads_rationale_68", "label": "One weekly bucket for the lead volume bar/line chart.", "file_type": "rationale", "source_file": "backend/app/schemas/leads.py", "source_location": "L68"}, {"id": "schemas_leads_rationale_80", "label": "Share of leads from a single acquisition source.", "file_type": "rationale", "source_file": "backend/app/schemas/leads.py", "source_location": "L80"}, {"id": "schemas_leads_rationale_93", "label": "One horizontal bar in the sales funnel visualisation.", "file_type": "rationale", "source_file": "backend/app/schemas/leads.py", "source_location": "L93"}, {"id": "schemas_leads_rationale_106", "label": "Full stats payload returned by GET /api/v1/leads/stats.", "file_type": "rationale", "source_file": "backend/app/schemas/leads.py", "source_location": "L106"}, {"id": "schemas_leads_rationale_120", "label": "Minimal call row for the lead detail activity timeline.      ``processed_date``", "file_type": "rationale", "source_file": "backend/app/schemas/leads.py", "source_location": "L120"}, {"id": "schemas_leads_rationale_154", "label": "One staff journal entry rendered on the lead detail timeline.", "file_type": "rationale", "source_file": "backend/app/schemas/leads.py", "source_location": "L154"}, {"id": "schemas_leads_rationale_164", "label": "Full payload for GET /api/v1/leads/{id}.      `notes_raw` carries the immutable", "file_type": "rationale", "source_file": "backend/app/schemas/leads.py", "source_location": "L164"}, {"id": "schemas_leads_rationale_189", "label": "Partial-update payload for PATCH /api/v1/leads/{id}.      All fields optional; o", "file_type": "rationale", "source_file": "backend/app/schemas/leads.py", "source_location": "L189"}, {"id": "schemas_leads_rationale_202", "label": "Payload for POST /api/v1/leads/{id}/notes.", "file_type": "rationale", "source_file": "backend/app/schemas/leads.py", "source_location": "L202"}, {"id": "schemas_leads_rationale_213", "label": "One row in the lead's audit-log timeline.      `action` is a dotted string like", "file_type": "rationale", "source_file": "backend/app/schemas/leads.py", "source_location": "L213"}, {"id": "schemas_leads_rationale_233", "label": "Full history payload returned by GET /api/v1/leads/{id}/history.      Events are", "file_type": "rationale", "source_file": "backend/app/schemas/leads.py", "source_location": "L233"}, {"id": "schemas_leads_rationale_249", "label": "Filename + size + mime for one attachment. No bytes.", "file_type": "rationale", "source_file": "backend/app/schemas/leads.py", "source_location": "L249"}, {"id": "schemas_leads_rationale_257", "label": "One message in a thread. Body is plain-text only.", "file_type": "rationale", "source_file": "backend/app/schemas/leads.py", "source_location": "L257"}, {"id": "schemas_leads_rationale_271", "label": "One Gmail thread linked to a lead, with its messages nested.", "file_type": "rationale", "source_file": "backend/app/schemas/leads.py", "source_location": "L271"}, {"id": "schemas_leads_rationale_281", "label": "Full payload for ``GET /api/v1/leads/{id}/emails``.      Threads are ordered new", "file_type": "rationale", "source_file": "backend/app/schemas/leads.py", "source_location": "L281"}, {"id": "schemas_leads_rationale_291", "label": "One Drive file shared with this lead's email address.", "file_type": "rationale", "source_file": "backend/app/schemas/leads.py", "source_location": "L291"}, {"id": "schemas_leads_rationale_304", "label": "Payload for ``GET /api/v1/leads/{id}/documents``.      Files are ordered newest-", "file_type": "rationale", "source_file": "backend/app/schemas/leads.py", "source_location": "L304"}], "edges": [{"source": "users_jinangokotano_documents_agentic_builder_projects_central_intelligence_backend_app_schemas_leads_py", "target": "pydantic", "relation": "imports_from", "context": "import", "confidence": "EXTRACTED", "source_file": "backend/app/schemas/leads.py", "source_location": "L17", "weight": 1.0}, {"source": "users_jinangokotano_documents_agentic_builder_projects_central_intelligence_backend_app_schemas_leads_py", "target": "schemas_leads_leadrecord", "relation": "contains", "confidence": "EXTRACTED", "source_file": "backend/app/schemas/leads.py", "source_location": "L25", "weight": 1.0}, {"source": "schemas_leads_leadrecord", "target": "basemodel", "relation": "inherits", "confidence": "EXTRACTED", "source_file": "backend/app/schemas/leads.py", "source_location": "L25", "weight": 1.0}, {"source": "users_jinangokotano_documents_agentic_builder_projects_central_intelligence_backend_app_schemas_leads_py", "target": "schemas_leads_leadlistresponse", "relation": "contains", "confidence": "EXTRACTED", "source_file": "backend/app/schemas/leads.py", "source_location": "L39", "weight": 1.0}, {"source": "schemas_leads_leadlistresponse", "target": "basemodel", "relation": "inherits", "confidence": "EXTRACTED", "source_file": "backend/app/schemas/leads.py", "source_location": "L39", "weight": 1.0}, {"source": "users_jinangokotano_documents_agentic_builder_projects_central_intelligence_backend_app_schemas_leads_py", "target": "schemas_leads_leadskpiresponse", "relation": "contains", "confidence": "EXTRACTED", "source_file": "backend/app/schemas/leads.py", "source_location": "L53", "weight": 1.0}, {"source": "schemas_leads_leadskpiresponse", "target": "basemodel", "relation": "inherits", "confidence": "EXTRACTED", "source_file": "backend/app/schemas/leads.py", "source_location": "L53", "weight": 1.0}, {"source": "users_jinangokotano_documents_agentic_builder_projects_central_intelligence_backend_app_schemas_leads_py", "target": "schemas_leads_leadvolumepoint", "relation": "contains", "confidence": "EXTRACTED", "source_file": "backend/app/schemas/leads.py", "source_location": "L67", "weight": 1.0}, {"source": "schemas_leads_leadvolumepoint", "target": "basemodel", "relation": "inherits", "confidence": "EXTRACTED", "source_file": "backend/app/schemas/leads.py", "source_location": "L67", "weight": 1.0}, {"source": "users_jinangokotano_documents_agentic_builder_projects_central_intelligence_backend_app_schemas_leads_py", "target": "schemas_leads_sourcebreakdownitem", "relation": "contains", "confidence": "EXTRACTED", "source_file": "backend/app/schemas/leads.py", "source_location": "L79", "weight": 1.0}, {"source": "schemas_leads_sourcebreakdownitem", "target": "basemodel", "relation": "inherits", "confidence": "EXTRACTED", "source_file": "backend/app/schemas/leads.py", "source_location": "L79", "weight": 1.0}, {"source": "users_jinangokotano_documents_agentic_builder_projects_central_intelligence_backend_app_schemas_leads_py", "target": "schemas_leads_funnelstage", "relation": "contains", "confidence": "EXTRACTED", "source_file": "backend/app/schemas/leads.py", "source_location": "L92", "weight": 1.0}, {"source": "schemas_leads_funnelstage", "target": "basemodel", "relation": "inherits", "confidence": "EXTRACTED", "source_file": "backend/app/schemas/leads.py", "source_location": "L92", "weight": 1.0}, {"source": "users_jinangokotano_documents_agentic_builder_projects_central_intelligence_backend_app_schemas_leads_py", "target": "schemas_leads_leadsstatsresponse", "relation": "contains", "confidence": "EXTRACTED", "source_file": "backend/app/schemas/leads.py", "source_location": "L105", "weight": 1.0}, {"source": "schemas_leads_leadsstatsresponse", "target": "basemodel", "relation": "inherits", "confidence": "EXTRACTED", "source_file": "backend/app/schemas/leads.py", "source_location": "L105", "weight": 1.0}, {"source": "users_jinangokotano_documents_agentic_builder_projects_central_intelligence_backend_app_schemas_leads_py", "target": "schemas_leads_leadcallsummary", "relation": "contains", "confidence": "EXTRACTED", "source_file": "backend/app/schemas/leads.py", "source_location": "L119", "weight": 1.0}, {"source": "schemas_leads_leadcallsummary", "target": "basemodel", "relation": "inherits", "confidence": "EXTRACTED", "source_file": "backend/app/schemas/leads.py", "source_location": "L119", "weight": 1.0}, {"source": "users_jinangokotano_documents_agentic_builder_projects_central_intelligence_backend_app_schemas_leads_py", "target": "schemas_leads_leadgoalsummary", "relation": "contains", "confidence": "EXTRACTED", "source_file": "backend/app/schemas/leads.py", "source_location": "L134", "weight": 1.0}, {"source": "schemas_leads_leadgoalsummary", "target": "basemodel", "relation": "inherits", "confidence": "EXTRACTED", "source_file": "backend/app/schemas/leads.py", "source_location": "L134", "weight": 1.0}, {"source": "users_jinangokotano_documents_agentic_builder_projects_central_intelligence_backend_app_schemas_leads_py", "target": "schemas_leads_leadpainpointsummary", "relation": "contains", "confidence": "EXTRACTED", "source_file": "backend/app/schemas/leads.py", "source_location": "L141", "weight": 1.0}, {"source": "schemas_leads_leadpainpointsummary", "target": "basemodel", "relation": "inherits", "confidence": "EXTRACTED", "source_file": "backend/app/schemas/leads.py", "source_location": "L141", "weight": 1.0}, {"source": "users_jinangokotano_documents_agentic_builder_projects_central_intelligence_backend_app_schemas_leads_py", "target": "schemas_leads_leadobjectionsummary", "relation": "contains", "confidence": "EXTRACTED", "source_file": "backend/app/schemas/leads.py", "source_location": "L147", "weight": 1.0}, {"source": "schemas_leads_leadobjectionsummary", "target": "basemodel", "relation": "inherits", "confidence": "EXTRACTED", "source_file": "backend/app/schemas/leads.py", "source_location": "L147", "weight": 1.0}, {"source": "users_jinangokotano_documents_agentic_builder_projects_central_intelligence_backend_app_schemas_leads_py", "target": "schemas_leads_noterow", "relation": "contains", "confidence": "EXTRACTED", "source_file": "backend/app/schemas/leads.py", "source_location": "L153", "weight": 1.0}, {"source": "schemas_leads_noterow", "target": "basemodel", "relation": "inherits", "confidence": "EXTRACTED", "source_file": "backend/app/schemas/leads.py", "source_location": "L153", "weight": 1.0}, {"source": "users_jinangokotano_documents_agentic_builder_projects_central_intelligence_backend_app_schemas_leads_py", "target": "schemas_leads_leaddetailresponse", "relation": "contains", "confidence": "EXTRACTED", "source_file": "backend/app/schemas/leads.py", "source_location": "L163", "weight": 1.0}, {"source": "schemas_leads_leaddetailresponse", "target": "basemodel", "relation": "inherits", "confidence": "EXTRACTED", "source_file": "backend/app/schemas/leads.py", "source_location": "L163", "weight": 1.0}, {"source": "users_jinangokotano_documents_agentic_builder_projects_central_intelligence_backend_app_schemas_leads_py", "target": "schemas_leads_updateleadrequest", "relation": "contains", "confidence": "EXTRACTED", "source_file": "backend/app/schemas/leads.py", "source_location": "L188", "weight": 1.0}, {"source": "schemas_leads_updateleadrequest", "target": "basemodel", "relation": "inherits", "confidence": "EXTRACTED", "source_file": "backend/app/schemas/leads.py", "source_location": "L188", "weight": 1.0}, {"source": "users_jinangokotano_documents_agentic_builder_projects_central_intelligence_backend_app_schemas_leads_py", "target": "schemas_leads_createnoterequest", "relation": "contains", "confidence": "EXTRACTED", "source_file": "backend/app/schemas/leads.py", "source_location": "L201", "weight": 1.0}, {"source": "schemas_leads_createnoterequest", "target": "basemodel", "relation": "inherits", "confidence": "EXTRACTED", "source_file": "backend/app/schemas/leads.py", "source_location": "L201", "weight": 1.0}, {"source": "users_jinangokotano_documents_agentic_builder_projects_central_intelligence_backend_app_schemas_leads_py", "target": "schemas_leads_leadhistoryevent", "relation": "contains", "confidence": "EXTRACTED", "source_file": "backend/app/schemas/leads.py", "source_location": "L212", "weight": 1.0}, {"source": "schemas_leads_leadhistoryevent", "target": "basemodel", "relation": "inherits", "confidence": "EXTRACTED", "source_file": "backend/app/schemas/leads.py", "source_location": "L212", "weight": 1.0}, {"source": "users_jinangokotano_documents_agentic_builder_projects_central_intelligence_backend_app_schemas_leads_py", "target": "schemas_leads_leadhistoryresponse", "relation": "contains", "confidence": "EXTRACTED", "source_file": "backend/app/schemas/leads.py", "source_location": "L232", "weight": 1.0}, {"source": "schemas_leads_leadhistoryresponse", "target": "basemodel", "relation": "inherits", "confidence": "EXTRACTED", "source_file": "backend/app/schemas/leads.py", "source_location": "L232", "weight": 1.0}, {"source": "users_jinangokotano_documents_agentic_builder_projects_central_intelligence_backend_app_schemas_leads_py", "target": "schemas_leads_emailattachmentmeta", "relation": "contains", "confidence": "EXTRACTED", "source_file": "backend/app/schemas/leads.py", "source_location": "L248", "weight": 1.0}, {"source": "schemas_leads_emailattachmentmeta", "target": "basemodel", "relation": "inherits", "confidence": "EXTRACTED", "source_file": "backend/app/schemas/leads.py", "source_location": "L248", "weight": 1.0}, {"source": "users_jinangokotano_documents_agentic_builder_projects_central_intelligence_backend_app_schemas_leads_py", "target": "schemas_leads_emailmessagerow", "relation": "contains", "confidence": "EXTRACTED", "source_file": "backend/app/schemas/leads.py", "source_location": "L256", "weight": 1.0}, {"source": "schemas_leads_emailmessagerow", "target": "basemodel", "relation": "inherits", "confidence": "EXTRACTED", "source_file": "backend/app/schemas/leads.py", "source_location": "L256", "weight": 1.0}, {"source": "users_jinangokotano_documents_agentic_builder_projects_central_intelligence_backend_app_schemas_leads_py", "target": "schemas_leads_emailthreadrow", "relation": "contains", "confidence": "EXTRACTED", "source_file": "backend/app/schemas/leads.py", "source_location": "L270", "weight": 1.0}, {"source": "schemas_leads_emailthreadrow", "target": "basemodel", "relation": "inherits", "confidence": "EXTRACTED", "source_file": "backend/app/schemas/leads.py", "source_location": "L270", "weight": 1.0}, {"source": "users_jinangokotano_documents_agentic_builder_projects_central_intelligence_backend_app_schemas_leads_py", "target": "schemas_leads_emailthreadsresponse", "relation": "contains", "confidence": "EXTRACTED", "source_file": "backend/app/schemas/leads.py", "source_location": "L280", "weight": 1.0}, {"source": "schemas_leads_emailthreadsresponse", "target": "basemodel", "relation": "inherits", "confidence": "EXTRACTED", "source_file": "backend/app/schemas/leads.py", "source_location": "L280", "weight": 1.0}, {"source": "users_jinangokotano_documents_agentic_builder_projects_central_intelligence_backend_app_schemas_leads_py", "target": "schemas_leads_documentrow", "relation": "contains", "confidence": "EXTRACTED", "source_file": "backend/app/schemas/leads.py", "source_location": "L290", "weight": 1.0}, {"source": "schemas_leads_documentrow", "target": "basemodel", "relation": "inherits", "confidence": "EXTRACTED", "source_file": "backend/app/schemas/leads.py", "source_location": "L290", "weight": 1.0}, {"source": "users_jinangokotano_documents_agentic_builder_projects_central_intelligence_backend_app_schemas_leads_py", "target": "schemas_leads_documentsresponse", "relation": "contains", "confidence": "EXTRACTED", "source_file": "backend/app/schemas/leads.py", "source_location": "L303", "weight": 1.0}, {"source": "schemas_leads_documentsresponse", "target": "basemodel", "relation": "inherits", "confidence": "EXTRACTED", "source_file": "backend/app/schemas/leads.py", "source_location": "L303", "weight": 1.0}, {"source": "schemas_leads_rationale_1", "target": "users_jinangokotano_documents_agentic_builder_projects_central_intelligence_backend_app_schemas_leads_py", "relation": "rationale_for", "confidence": "EXTRACTED", "source_file": "backend/app/schemas/leads.py", "source_location": "L1", "weight": 1.0}, {"source": "schemas_leads_rationale_26", "target": "schemas_leads_leadrecord", "relation": "rationale_for", "confidence": "EXTRACTED", "source_file": "backend/app/schemas/leads.py", "source_location": "L26", "weight": 1.0}, {"source": "schemas_leads_rationale_40", "target": "schemas_leads_leadlistresponse", "relation": "rationale_for", "confidence": "EXTRACTED", "source_file": "backend/app/schemas/leads.py", "source_location": "L40", "weight": 1.0}, {"source": "schemas_leads_rationale_68", "target": "schemas_leads_leadvolumepoint", "relation": "rationale_for", "confidence": "EXTRACTED", "source_file": "backend/app/schemas/leads.py", "source_location": "L68", "weight": 1.0}, {"source": "schemas_leads_rationale_80", "target": "schemas_leads_sourcebreakdownitem", "relation": "rationale_for", "confidence": "EXTRACTED", "source_file": "backend/app/schemas/leads.py", "source_location": "L80", "weight": 1.0}, {"source": "schemas_leads_rationale_93", "target": "schemas_leads_funnelstage", "relation": "rationale_for", "confidence": "EXTRACTED", "source_file": "backend/app/schemas/leads.py", "source_location": "L93", "weight": 1.0}, {"source": "schemas_leads_rationale_106", "target": "schemas_leads_leadsstatsresponse", "relation": "rationale_for", "confidence": "EXTRACTED", "source_file": "backend/app/schemas/leads.py", "source_location": "L106", "weight": 1.0}, {"source": "schemas_leads_rationale_120", "target": "schemas_leads_leadcallsummary", "relation": "rationale_for", "confidence": "EXTRACTED", "source_file": "backend/app/schemas/leads.py", "source_location": "L120", "weight": 1.0}, {"source": "schemas_leads_rationale_154", "target": "schemas_leads_noterow", "relation": "rationale_for", "confidence": "EXTRACTED", "source_file": "backend/app/schemas/leads.py", "source_location": "L154", "weight": 1.0}, {"source": "schemas_leads_rationale_164", "target": "schemas_leads_leaddetailresponse", "relation": "rationale_for", "confidence": "EXTRACTED", "source_file": "backend/app/schemas/leads.py", "source_location": "L164", "weight": 1.0}, {"source": "schemas_leads_rationale_189", "target": "schemas_leads_updateleadrequest", "relation": "rationale_for", "confidence": "EXTRACTED", "source_file": "backend/app/schemas/leads.py", "source_location": "L189", "weight": 1.0}, {"source": "schemas_leads_rationale_202", "target": "schemas_leads_createnoterequest", "relation": "rationale_for", "confidence": "EXTRACTED", "source_file": "backend/app/schemas/leads.py", "source_location": "L202", "weight": 1.0}, {"source": "schemas_leads_rationale_213", "target": "schemas_leads_leadhistoryevent", "relation": "rationale_for", "confidence": "EXTRACTED", "source_file": "backend/app/schemas/leads.py", "source_location": "L213", "weight": 1.0}, {"source": "schemas_leads_rationale_233", "target": "schemas_leads_leadhistoryresponse", "relation": "rationale_for", "confidence": "EXTRACTED", "source_file": "backend/app/schemas/leads.py", "source_location": "L233", "weight": 1.0}, {"source": "schemas_leads_rationale_249", "target": "schemas_leads_emailattachmentmeta", "relation": "rationale_for", "confidence": "EXTRACTED", "source_file": "backend/app/schemas/leads.py", "source_location": "L249", "weight": 1.0}, {"source": "schemas_leads_rationale_257", "target": "schemas_leads_emailmessagerow", "relation": "rationale_for", "confidence": "EXTRACTED", "source_file": "backend/app/schemas/leads.py", "source_location": "L257", "weight": 1.0}, {"source": "schemas_leads_rationale_271", "target": "schemas_leads_emailthreadrow", "relation": "rationale_for", "confidence": "EXTRACTED", "source_file": "backend/app/schemas/leads.py", "source_location": "L271", "weight": 1.0}, {"source": "schemas_leads_rationale_281", "target": "schemas_leads_emailthreadsresponse", "relation": "rationale_for", "confidence": "EXTRACTED", "source_file": "backend/app/schemas/leads.py", "source_location": "L281", "weight": 1.0}, {"source": "schemas_leads_rationale_291", "target": "schemas_leads_documentrow", "relation": "rationale_for", "confidence": "EXTRACTED", "source_file": "backend/app/schemas/leads.py", "source_location": "L291", "weight": 1.0}, {"source": "schemas_leads_rationale_304", "target": "schemas_leads_documentsresponse", "relation": "rationale_for", "confidence": "EXTRACTED", "source_file": "backend/app/schemas/leads.py", "source_location": "L304", "weight": 1.0}], "raw_calls": []}