{"nodes": [{"id": "supabase_client", "label": "supabase_client.py", "file_type": "code", "source_file": "projects/workerbee/backend/app/auth/supabase_client.py", "source_location": "L1"}, {"id": "supabase_client_build_client", "label": "_build_client()", "file_type": "code", "source_file": "projects/workerbee/backend/app/auth/supabase_client.py", "source_location": "L26"}, {"id": "supabase_client_get_supabase_client", "label": "get_supabase_client()", "file_type": "code", "source_file": "projects/workerbee/backend/app/auth/supabase_client.py", "source_location": "L59"}, {"id": "supabase_client_rationale_1", "label": "Supabase client factory.  Returns a configured ``supabase.Client`` instance when", "file_type": "rationale", "source_file": "projects/workerbee/backend/app/auth/supabase_client.py", "source_location": "L1"}, {"id": "supabase_client_rationale_27", "label": "Attempt to build a Supabase client from settings.      Returns the client on suc", "file_type": "rationale", "source_file": "projects/workerbee/backend/app/auth/supabase_client.py", "source_location": "L27"}, {"id": "supabase_client_rationale_60", "label": "Return the module-level Supabase client, or ``None`` in mock mode.      This fun", "file_type": "rationale", "source_file": "projects/workerbee/backend/app/auth/supabase_client.py", "source_location": "L60"}], "edges": [{"source": "supabase_client", "target": "logging", "relation": "imports", "confidence": "EXTRACTED", "source_file": "projects/workerbee/backend/app/auth/supabase_client.py", "source_location": "L13", "weight": 1.0}, {"source": "supabase_client", "target": "typing", "relation": "imports_from", "confidence": "EXTRACTED", "source_file": "projects/workerbee/backend/app/auth/supabase_client.py", "source_location": "L14", "weight": 1.0}, {"source": "supabase_client", "target": "app_config", "relation": "imports_from", "confidence": "EXTRACTED", "source_file": "projects/workerbee/backend/app/auth/supabase_client.py", "source_location": "L16", "weight": 1.0}, {"source": "supabase_client", "target": "supabase_client_build_client", "relation": "contains", "confidence": "EXTRACTED", "source_file": "projects/workerbee/backend/app/auth/supabase_client.py", "source_location": "L26", "weight": 1.0}, {"source": "supabase_client", "target": "supabase_client_get_supabase_client", "relation": "contains", "confidence": "EXTRACTED", "source_file": "projects/workerbee/backend/app/auth/supabase_client.py", "source_location": "L59", "weight": 1.0}, {"source": "supabase_client_rationale_1", "target": "supabase_client", "relation": "rationale_for", "confidence": "EXTRACTED", "source_file": "projects/workerbee/backend/app/auth/supabase_client.py", "source_location": "L1", "weight": 1.0}, {"source": "supabase_client_rationale_27", "target": "supabase_client_build_client", "relation": "rationale_for", "confidence": "EXTRACTED", "source_file": "projects/workerbee/backend/app/auth/supabase_client.py", "source_location": "L27", "weight": 1.0}, {"source": "supabase_client_rationale_60", "target": "supabase_client_get_supabase_client", "relation": "rationale_for", "confidence": "EXTRACTED", "source_file": "projects/workerbee/backend/app/auth/supabase_client.py", "source_location": "L60", "weight": 1.0}]}